{
  "type": "minecraft:chest",
  "pools": [
    {
      "rolls": {
        "min": 2.0,
        "max": 4.0,
        "type": "minecraft:uniform"
      },
      "entries": [
        {
          "type": "minecraft:item",
          "weight": 10,
          "functions": [
            {
              "function": "minecraft:set_count",
              "count": {
                "min": 2.0,
                "max": 4.0,
                "type": "minecraft:uniform"
              }
            }
          ],
          "name": "minecraft:charcoal"
        },
        {
          "type": "minecraft:item",
          "weight": 10,
          "functions": [
            {
              "function": "minecraft:set_count",
              "count": {
                "min": 2.0,
                "max": 4.0,
                "type": "minecraft:uniform"
              }
            }
          ],
          "name": "minecraft:coal"
        },
        {
          "type": "minecraft:item",
          "weight": 10,
          "functions": [
            {
              "function": "minecraft:set_count",
              "count": {
                "min": 2.0,
                "max": 4.0,
                "type": "minecraft:uniform"
              }
            }
          ],
          "name": "minecraft:torch"
        },
        {
          "type": "minecraft:item",
          "weight": 10,
          "functions": [
            {
              "function": "minecraft:set_count",
              "count": {
                "min": 3.0,
                "max": 5.0,
                "type": "minecraft:uniform"
              }
            }
          ],
          "name": "minecraft:stick"
        },
        {
          "type": "minecraft:item",
          "weight": 10,
          "name": "minecraft:diamond"
        },
        {
          "type": "minecraft:item",
          "weight": 10,
          "functions": [
            {
              "function": "minecraft:set_count",
              "count": {
                "min": 1.0,
                "max": 3.0,
                "type": "minecraft:uniform"
              }
            }
          ],
          "name": "iceandfire:sapphire_gem"
        }
      ]
    },
    {
      "conditions": [
        {
          "chance": 0.1,
          "condition": "minecraft:random_chance"
        }
      ],
      "entries": [
        {
          "type": "minecraft:item",
          "functions": [
            {
              "count": {
                "max": 1,
                "min": 0
              },
              "function": "minecraft:set_count"
            }
          ],
          "name": "minecraft:enchanted_golden_apple"
        }
      ],
      "rolls": 1
    },
    {
      "rolls": 1,
      "entries": [
        {
          "type": "minecraft:item",
          "name": "irons_spellbooks:arcane_essence",
          "functions": [
            {
              "function": "minecraft:set_count",
              "count": {
                "min": 2,
                "max": 4
              }
            }
          ]
        }
      ],
      "conditions": [
        {
          "condition": "minecraft:random_chance",
          "chance": 0.5
        }
      ]
    },
    {
      "rolls": 2,
      "entries": [
        {
          "type": "minecraft:item",
          "weight": 1,
          "name": "irons_spellbooks:scroll",
          "functions": [
            {
              "function": "irons_spellbooks:randomize_spell",
              "quality": {
                "min": 0.0,
                "max": 0.6
              }
            }
          ]
        },
        {
          "type": "minecraft:empty",
          "weight": 2
        }
      ]
    },
    {
      "rolls": 1,
      "entries": [
        {
          "type": "minecraft:item",
          "name": "irons_spellbooks:blank_rune"
        }
      ],
      "conditions": [
        {
          "condition": "minecraft:random_chance",
          "chance": 0.1
        }
      ]
    },
    {
      "rolls": 1,
      "entries": [
        {
          "type": "minecraft:loot_table",
          "name": "irons_spellbooks:magic_items/basic_curios"
        }
      ],
      "conditions": [
        {
          "condition": "minecraft:random_chance",
          "chance": 0.1
        }
      ]
    },
    {
      "rolls": 2,
      "entries": [
        {
          "type": "minecraft:loot_table",
          "name": "irons_spellbooks:magic_items/good_ink"
        }
      ],
      "conditions": [
        {
          "condition": "minecraft:random_chance",
          "chance": 0.15
        }
      ]
    }
  ]
}